<annotation>
	<folder>JPEGImages</folder>
	<filename>837.jpg</filename>
	<path>/Users/NeilHuang/Desktop/Deepfashion0821/voc/VOCdevkit/VOC2007/JPEGImages/837.jpg</path>
	<source>
		<database>Unknown</database>
	</source>
	<size>
		<width>362</width>
		<height>362</height>
		<depth>3</depth>
	</size>
	<segmented>0</segmented>
	<object>
		<name>S_short blouse</name>
		<pose>Unspecified</pose>
		<truncated>0</truncated>
		<difficult>0</difficult>
		<bndbox>
			<xmin>146</xmin>
			<ymin>55</ymin>
			<xmax>282</xmax>
			<ymax>218</ymax>
		</bndbox>
	</object>
	<object>
		<name>C_W_pants</name>
		<pose>Unspecified</pose>
		<truncated>1</truncated>
		<difficult>0</difficult>
		<bndbox>
			<xmin>149</xmin>
			<ymin>211</ymin>
			<xmax>288</xmax>
			<ymax>362</ymax>
		</bndbox>
	</object>
</annotation>
