<annotation>
	<folder>JPEGImages</folder>
	<filename>943.jpg</filename>
	<path>/Users/NeilHuang/Desktop/Deepfashion0821/voc/VOCdevkit/VOC2007/JPEGImages/943.jpg</path>
	<source>
		<database>Unknown</database>
	</source>
	<size>
		<width>362</width>
		<height>362</height>
		<depth>3</depth>
	</size>
	<segmented>0</segmented>
	<object>
		<name>C_short blouse</name>
		<pose>Unspecified</pose>
		<truncated>0</truncated>
		<difficult>0</difficult>
		<bndbox>
			<xmin>126</xmin>
			<ymin>28</ymin>
			<xmax>288</xmax>
			<ymax>207</ymax>
		</bndbox>
	</object>
	<object>
		<name>C_shorts</name>
		<pose>Unspecified</pose>
		<truncated>0</truncated>
		<difficult>0</difficult>
		<bndbox>
			<xmin>167</xmin>
			<ymin>204</ymin>
			<xmax>307</xmax>
			<ymax>329</ymax>
		</bndbox>
	</object>
	<object>
		<name>F_belt</name>
		<pose>Unspecified</pose>
		<truncated>0</truncated>
		<difficult>0</difficult>
		<bndbox>
			<xmin>168</xmin>
			<ymin>182</ymin>
			<xmax>297</xmax>
			<ymax>223</ymax>
		</bndbox>
	</object>
</annotation>
