<annotation>
	<folder>casual_W</folder>
	<filename>Casual_W124.jpg</filename>
	<path>C:\Users\&#38515;&#24609;&#38748;\Desktop\&#24037;&#20316;&#31359;&#33879;&#28310;&#21063;\casual_W\Casual_W124.jpg</path>
	<source>
		<database>Unknown</database>
	</source>
	<size>
		<width>200</width>
		<height>200</height>
		<depth>3</depth>
	</size>
	<segmented>0</segmented>
	<object>
		<name>C_T-shirt</name>
		<pose>Unspecified</pose>
		<truncated>0</truncated>
		<difficult>0</difficult>
		<bndbox>
			<xmin>44</xmin>
			<ymin>16</ymin>
			<xmax>160</xmax>
			<ymax>162</ymax>
		</bndbox>
	</object>
</annotation>