<annotation>
	<folder>temp_pic</folder>
	<filename>Casual_W1493.jpg</filename>
	<path>/Users/NeilHuang/Desktop/relabel/temp_pic/Casual_W1493.jpg</path>
	<source>
		<database>Unknown</database>
	</source>
	<size>
		<width>300</width>
		<height>300</height>
		<depth>3</depth>
	</size>
	<segmented>0</segmented>
	<object>
		<name>S_dress</name>
		<pose>Unspecified</pose>
		<truncated>0</truncated>
		<difficult>0</difficult>
		<bndbox>
			<xmin>196</xmin>
			<ymin>44</ymin>
			<xmax>278</xmax>
			<ymax>149</ymax>
		</bndbox>
	</object>
	<object>
		<name>face_W</name>
		<pose>Unspecified</pose>
		<truncated>0</truncated>
		<difficult>0</difficult>
		<bndbox>
			<xmin>224</xmin>
			<ymin>9</ymin>
			<xmax>240</xmax>
			<ymax>25</ymax>
		</bndbox>
	</object>
	<object>
		<name>C_tank top</name>
		<pose>Unspecified</pose>
		<truncated>0</truncated>
		<difficult>0</difficult>
		<bndbox>
			<xmin>60</xmin>
			<ymin>49</ymin>
			<xmax>128</xmax>
			<ymax>130</ymax>
		</bndbox>
	</object>
	<object>
		<name>C_tank top</name>
		<pose>Unspecified</pose>
		<truncated>0</truncated>
		<difficult>0</difficult>
		<bndbox>
			<xmin>211</xmin>
			<ymin>29</ymin>
			<xmax>258</xmax>
			<ymax>80</ymax>
		</bndbox>
	</object>
</annotation>
