<annotation>
	<folder>temp_pic</folder>
	<filename>Casual_W103.jpg</filename>
	<path>/Users/NeilHuang/Desktop/relabel/temp_pic/Casual_W103.jpg</path>
	<source>
		<database>Unknown</database>
	</source>
	<size>
		<width>277</width>
		<height>277</height>
		<depth>3</depth>
	</size>
	<segmented>0</segmented>
	<object>
		<name>C_dress</name>
		<pose>Unspecified</pose>
		<truncated>0</truncated>
		<difficult>0</difficult>
		<bndbox>
			<xmin>66</xmin>
			<ymin>14</ymin>
			<xmax>201</xmax>
			<ymax>266</ymax>
		</bndbox>
	</object>
	<object>
		<name>C_skirt</name>
		<pose>Unspecified</pose>
		<truncated>0</truncated>
		<difficult>0</difficult>
		<bndbox>
			<xmin>77</xmin>
			<ymin>122</ymin>
			<xmax>187</xmax>
			<ymax>265</ymax>
		</bndbox>
	</object>
</annotation>
