<annotation>
	<folder>temp_pic</folder>
	<filename>Dale_F_belt369.jpg</filename>
	<path>/Users/NeilHuang/Desktop/relabel/temp_pic/Dale_F_belt369.jpg</path>
	<source>
		<database>Unknown</database>
	</source>
	<size>
		<width>533</width>
		<height>800</height>
		<depth>3</depth>
	</size>
	<segmented>0</segmented>
	<object>
		<name>F_belt</name>
		<pose>Unspecified</pose>
		<truncated>0</truncated>
		<difficult>0</difficult>
		<bndbox>
			<xmin>161</xmin>
			<ymin>635</ymin>
			<xmax>298</xmax>
			<ymax>686</ymax>
		</bndbox>
	</object>
	<object>
		<name>F_M_suit jacket</name>
		<pose>Unspecified</pose>
		<truncated>0</truncated>
		<difficult>0</difficult>
		<bndbox>
			<xmin>65</xmin>
			<ymin>275</ymin>
			<xmax>480</xmax>
			<ymax>751</ymax>
		</bndbox>
	</object>
	<object>
		<name>F_tie</name>
		<pose>Unspecified</pose>
		<truncated>0</truncated>
		<difficult>0</difficult>
		<bndbox>
			<xmin>210</xmin>
			<ymin>287</ymin>
			<xmax>271</xmax>
			<ymax>415</ymax>
		</bndbox>
	</object>
</annotation>
