<annotation>
	<folder>temp_pic</folder>
	<filename>F_tailored-skirt459.jpg</filename>
	<path>/Users/NeilHuang/Desktop/relabel/temp_pic/F_tailored-skirt459.jpg</path>
	<source>
		<database>Unknown</database>
	</source>
	<size>
		<width>225</width>
		<height>225</height>
		<depth>3</depth>
	</size>
	<segmented>0</segmented>
	<object>
		<name>F_tailored skirt</name>
		<pose>Unspecified</pose>
		<truncated>0</truncated>
		<difficult>0</difficult>
		<bndbox>
			<xmin>36</xmin>
			<ymin>71</ymin>
			<xmax>87</xmax>
			<ymax>141</ymax>
		</bndbox>
	</object>
	<object>
		<name>F_tailored skirt</name>
		<pose>Unspecified</pose>
		<truncated>1</truncated>
		<difficult>0</difficult>
		<bndbox>
			<xmin>110</xmin>
			<ymin>32</ymin>
			<xmax>225</xmax>
			<ymax>199</ymax>
		</bndbox>
	</object>
	<object>
		<name>F_shirt</name>
		<pose>Unspecified</pose>
		<truncated>0</truncated>
		<difficult>0</difficult>
		<bndbox>
			<xmin>31</xmin>
			<ymin>30</ymin>
			<xmax>88</xmax>
			<ymax>76</ymax>
		</bndbox>
	</object>
</annotation>
