<?xml version='1.0' encoding='utf-8'?>
<annotation>
	<folder>Formal</folder>
	<filename>Formal_M309.jpg</filename>
	<path>C:\Users\Dale\Desktop\工作穿著準則-20190708T072430Z-001\Formal\Formal_M309.jpg</path>
	<source>
		<database>Unknown</database>
	</source>
	<size>
		<width>241</width>
		<height>300</height>
		<depth>3</depth>
	</size>
	<segmented>0</segmented>
	<object>
		<name>F_belt</name>
		<pose>Unspecified</pose>
		<truncated>0</truncated>
		<difficult>0</difficult>
		<bndbox>
			<xmin>106</xmin>
			<ymin>234</ymin>
			<xmax>160</xmax>
			<ymax>259</ymax>
		</bndbox>
	</object>
	<object>
		<name>F_M_suit jacket</name>
		<pose>Unspecified</pose>
		<truncated>0</truncated>
		<difficult>0</difficult>
		<bndbox>
			<xmin>37</xmin>
			<ymin>85</ymin>
			<xmax>206</xmax>
			<ymax>270</ymax>
		</bndbox>
	</object>
	<object>
		<name>F_dress pants</name>
		<pose>Unspecified</pose>
		<truncated>0</truncated>
		<difficult>0</difficult>
		<bndbox>
			<xmin>62</xmin>
			<ymin>248</ymin>
			<xmax>194</xmax>
			<ymax>299</ymax>
		</bndbox>
	</object>
	<object>
		<name>face_M</name>
		<pose>Unspecified</pose>
		<truncated>0</truncated>
		<difficult>0</difficult>
		<bndbox>
			<xmin>101</xmin>
			<ymin>22</ymin>
			<xmax>146</xmax>
			<ymax>73</ymax>
		</bndbox>
	</object>
</annotation>