<?xml version='1.0' encoding='utf-8'?>
<annotation>
	<folder>Formal</folder>
	<filename>Formal_M222.jpg</filename>
	<path>C:\Users\Dale\Desktop\工作穿著準則-20190708T072430Z-001\Formal\Formal_M222.jpg</path>
	<source>
		<database>Unknown</database>
	</source>
	<size>
		<width>201</width>
		<height>301</height>
		<depth>3</depth>
	</size>
	<segmented>0</segmented>
	<object>
		<name>face_M</name>
		<pose>Unspecified</pose>
		<truncated>0</truncated>
		<difficult>0</difficult>
		<bndbox>
			<xmin>90</xmin>
			<ymin>38</ymin>
			<xmax>111</xmax>
			<ymax>63</ymax>
		</bndbox>
	</object>
	<object>
		<name>C_M_pants</name>
		<pose>Unspecified</pose>
		<truncated>0</truncated>
		<difficult>0</difficult>
		<bndbox>
			<xmin>68</xmin>
			<ymin>140</ymin>
			<xmax>122</xmax>
			<ymax>244</ymax>
		</bndbox>
	</object>
	<object>
		<name>C_sneakers</name>
		<pose>Unspecified</pose>
		<truncated>0</truncated>
		<difficult>0</difficult>
		<bndbox>
			<xmin>67</xmin>
			<ymin>257</ymin>
			<xmax>86</xmax>
			<ymax>283</ymax>
		</bndbox>
	</object>
	<object>
		<name>C_sneakers</name>
		<pose>Unspecified</pose>
		<truncated>0</truncated>
		<difficult>0</difficult>
		<bndbox>
			<xmin>87</xmin>
			<ymin>265</ymin>
			<xmax>105</xmax>
			<ymax>286</ymax>
		</bndbox>
	</object>
</annotation>