<?xml version='1.0' encoding='utf-8'?>
<annotation>
	<folder>temp_picture</folder>
	<filename>Formal_W410.jpg</filename>
	<path>/Users/NeilHuang/Desktop/工作/中國信託/輪調/視覺實驗室/風格辨識/All_xml_img_data/temp_picture/Formal_W410.jpg</path>
	<source>
		<database>Unknown</database>
	</source>
	<size>
		<width>300</width>
		<height>300</height>
		<depth>3</depth>
	</size>
	<segmented>0</segmented>
	<object>
		<name>face_W</name>
		<pose>Unspecified</pose>
		<truncated>0</truncated>
		<difficult>0</difficult>
		<bndbox>
			<xmin>98</xmin>
			<ymin>32</ymin>
			<xmax>123</xmax>
			<ymax>57</ymax>
		</bndbox>
	</object>
	<object>
		<name>C_long sleeve</name>
		<pose>Unspecified</pose>
		<truncated>0</truncated>
		<difficult>0</difficult>
		<bndbox>
			<xmin>65</xmin>
			<ymin>47</ymin>
			<xmax>148</xmax>
			<ymax>153</ymax>
		</bndbox>
	</object>
	<object>
		<name>F_W_pants</name>
		<pose>Unspecified</pose>
		<truncated>0</truncated>
		<difficult>0</difficult>
		<bndbox>
			<xmin>77</xmin>
			<ymin>119</ymin>
			<xmax>161</xmax>
			<ymax>274</ymax>
		</bndbox>
	</object>
	<object>
		<name>S_pumps</name>
		<pose>Unspecified</pose>
		<truncated>0</truncated>
		<difficult>0</difficult>
		<bndbox>
			<xmin>92</xmin>
			<ymin>265</ymin>
			<xmax>162</xmax>
			<ymax>296</ymax>
		</bndbox>
	</object>
</annotation>