<?xml version='1.0' encoding='utf-8'?>
<annotation>
	<folder>放這</folder>
	<filename>Smart casual_M1029.jpg</filename>
	<path>C:\Users\wu870225\Downloads\放這\Smart casual_M1029.jpg</path>
	<source>
		<database>Unknown</database>
	</source>
	<size>
		<width>626</width>
		<height>800</height>
		<depth>3</depth>
	</size>
	<segmented>0</segmented>
	<object>
		<name>face_M</name>
		<pose>Unspecified</pose>
		<truncated>0</truncated>
		<difficult>0</difficult>
		<bndbox>
			<xmin>311</xmin>
			<ymin>49</ymin>
			<xmax>371</xmax>
			<ymax>118</ymax>
		</bndbox>
	</object>
	<object>
		<name>C_shirt</name>
		<pose>Unspecified</pose>
		<truncated>0</truncated>
		<difficult>0</difficult>
		<bndbox>
			<xmin>219</xmin>
			<ymin>121</ymin>
			<xmax>444</xmax>
			<ymax>425</ymax>
		</bndbox>
	</object>
	<object>
		<name>C_jeans</name>
		<pose>Unspecified</pose>
		<truncated>0</truncated>
		<difficult>0</difficult>
		<bndbox>
			<xmin>232</xmin>
			<ymin>425</ymin>
			<xmax>414</xmax>
			<ymax>725</ymax>
		</bndbox>
	</object>
	<object>
		<name>C_sneakers</name>
		<pose>Unspecified</pose>
		<truncated>0</truncated>
		<difficult>0</difficult>
		<bndbox>
			<xmin>217</xmin>
			<ymin>722</ymin>
			<xmax>457</xmax>
			<ymax>792</ymax>
		</bndbox>
	</object>
</annotation>