<?xml version='1.0' encoding='utf-8'?>
<annotation>
	<folder>Smart casual_W</folder>
	<filename>Smart casual_W29.jpg</filename>
	<path>C:\Users\yunch\Desktop\工作穿著準則\Smart casual_W\Smart casual_W29.jpg</path>
	<source>
		<database>Unknown</database>
	</source>
	<size>
		<width>236</width>
		<height>346</height>
		<depth>3</depth>
	</size>
	<segmented>0</segmented>
	<object>
		<name>face_W</name>
		<pose>Unspecified</pose>
		<truncated>0</truncated>
		<difficult>0</difficult>
		<bndbox>
			<xmin>107</xmin>
			<ymin>17</ymin>
			<xmax>154</xmax>
			<ymax>68</ymax>
		</bndbox>
	</object>
	<object>
		<name>C_tank top</name>
		<pose>Unspecified</pose>
		<truncated>0</truncated>
		<difficult>0</difficult>
		<bndbox>
			<xmin>74</xmin>
			<ymin>70</ymin>
			<xmax>177</xmax>
			<ymax>186</ymax>
		</bndbox>
	</object>
	<object>
		<name>F_tailored skirt</name>
		<pose>Unspecified</pose>
		<truncated>0</truncated>
		<difficult>0</difficult>
		<bndbox>
			<xmin>72</xmin>
			<ymin>171</ymin>
			<xmax>176</xmax>
			<ymax>337</ymax>
		</bndbox>
	</object>
</annotation>