<?xml version='1.0' encoding='utf-8'?>
<annotation>
	<folder>Smart casual_W</folder>
	<filename>Smart casual_W289.jpg</filename>
	<path>C:\Users\yunch\Desktop\工作穿著準則\Smart casual_W\Smart casual_W289.jpg</path>
	<source>
		<database>Unknown</database>
	</source>
	<size>
		<width>205</width>
		<height>300</height>
		<depth>3</depth>
	</size>
	<segmented>0</segmented>
	<object>
		<name>face_W</name>
		<pose>Unspecified</pose>
		<truncated>0</truncated>
		<difficult>0</difficult>
		<bndbox>
			<xmin>94</xmin>
			<ymin>32</ymin>
			<xmax>122</xmax>
			<ymax>69</ymax>
		</bndbox>
	</object>
	<object>
		<name>C_hat</name>
		<pose>Unspecified</pose>
		<truncated>0</truncated>
		<difficult>0</difficult>
		<bndbox>
			<xmin>56</xmin>
			<ymin>2</ymin>
			<xmax>158</xmax>
			<ymax>56</ymax>
		</bndbox>
	</object>
	<object>
		<name>C_shorts</name>
		<pose>Unspecified</pose>
		<truncated>0</truncated>
		<difficult>0</difficult>
		<bndbox>
			<xmin>55</xmin>
			<ymin>190</ymin>
			<xmax>172</xmax>
			<ymax>273</ymax>
		</bndbox>
	</object>
	<object>
		<name>C_tank top</name>
		<pose>Unspecified</pose>
		<truncated>0</truncated>
		<difficult>0</difficult>
		<bndbox>
			<xmin>53</xmin>
			<ymin>81</ymin>
			<xmax>151</xmax>
			<ymax>179</ymax>
		</bndbox>
	</object>
</annotation>