<annotation>
	<folder>temp_pic</folder>
	<filename>Abby_F_shirt352.jpg</filename>
	<path>/Users/NeilHuang/Desktop/relabel/temp_pic/Abby_F_shirt352.jpg</path>
	<source>
		<database>Unknown</database>
	</source>
	<size>
		<width>225</width>
		<height>225</height>
		<depth>3</depth>
	</size>
	<segmented>0</segmented>
	<object>
		<name>F_shirt</name>
		<pose>Unspecified</pose>
		<truncated>0</truncated>
		<difficult>0</difficult>
		<bndbox>
			<xmin>57</xmin>
			<ymin>62</ymin>
			<xmax>175</xmax>
			<ymax>182</ymax>
		</bndbox>
	</object>
	<object>
		<name>F_tailored skirt</name>
		<pose>Unspecified</pose>
		<truncated>1</truncated>
		<difficult>0</difficult>
		<bndbox>
			<xmin>72</xmin>
			<ymin>174</ymin>
			<xmax>161</xmax>
			<ymax>225</ymax>
		</bndbox>
	</object>
</annotation>
