<annotation>
	<folder>temp_pic</folder>
	<filename>Albert_F_shirt(433).jpg</filename>
	<path>/Users/NeilHuang/Desktop/relabel/temp_pic/Albert_F_shirt(433).jpg</path>
	<source>
		<database>Unknown</database>
	</source>
	<size>
		<width>173</width>
		<height>280</height>
		<depth>3</depth>
	</size>
	<segmented>0</segmented>
	<object>
		<name>F_shirt</name>
		<pose>Unspecified</pose>
		<truncated>0</truncated>
		<difficult>0</difficult>
		<bndbox>
			<xmin>12</xmin>
			<ymin>88</ymin>
			<xmax>157</xmax>
			<ymax>220</ymax>
		</bndbox>
	</object>
	<object>
		<name>F_tailored skirt</name>
		<pose>Unspecified</pose>
		<truncated>0</truncated>
		<difficult>0</difficult>
		<bndbox>
			<xmin>38</xmin>
			<ymin>199</ymin>
			<xmax>132</xmax>
			<ymax>259</ymax>
		</bndbox>
	</object>
</annotation>
