<annotation>
	<folder>temp_pic</folder>
	<filename>blazer(307).jpg</filename>
	<path>/Users/NeilHuang/Desktop/relabel/temp_pic/blazer(307).jpg</path>
	<source>
		<database>Unknown</database>
	</source>
	<size>
		<width>173</width>
		<height>280</height>
		<depth>3</depth>
	</size>
	<segmented>0</segmented>
	<object>
		<name>F_M_suit jacket</name>
		<pose>Unspecified</pose>
		<truncated>0</truncated>
		<difficult>0</difficult>
		<bndbox>
			<xmin>8</xmin>
			<ymin>43</ymin>
			<xmax>163</xmax>
			<ymax>214</ymax>
		</bndbox>
	</object>
	<object>
		<name>F_dress pants</name>
		<pose>Unspecified</pose>
		<truncated>0</truncated>
		<difficult>0</difficult>
		<bndbox>
			<xmin>41</xmin>
			<ymin>187</ymin>
			<xmax>115</xmax>
			<ymax>260</ymax>
		</bndbox>
	</object>
</annotation>
