<annotation>
	<folder>temp_pic</folder>
	<filename>F_tailored-skirt84.jpg</filename>
	<path>/Users/NeilHuang/Desktop/relabel/temp_pic/F_tailored-skirt84.jpg</path>
	<source>
		<database>Unknown</database>
	</source>
	<size>
		<width>191</width>
		<height>255</height>
		<depth>3</depth>
	</size>
	<segmented>0</segmented>
	<object>
		<name>F_tailored skirt</name>
		<pose>Unspecified</pose>
		<truncated>0</truncated>
		<difficult>0</difficult>
		<bndbox>
			<xmin>49</xmin>
			<ymin>126</ymin>
			<xmax>133</xmax>
			<ymax>240</ymax>
		</bndbox>
	</object>
	<object>
		<name>F_shirt</name>
		<pose>Unspecified</pose>
		<truncated>0</truncated>
		<difficult>0</difficult>
		<bndbox>
			<xmin>42</xmin>
			<ymin>51</ymin>
			<xmax>144</xmax>
			<ymax>147</ymax>
		</bndbox>
	</object>
</annotation>
