<?xml version='1.0' encoding='utf-8'?>
<annotation>
	<folder>Formal4</folder>
	<filename>Formal_M99.jpg</filename>
	<path>C:\Users\Dale\Desktop\工作穿著準則-20190708T072430Z-001\Formal4\Formal_M99.jpg</path>
	<source>
		<database>Unknown</database>
	</source>
	<size>
		<width>257</width>
		<height>300</height>
		<depth>3</depth>
	</size>
	<segmented>0</segmented>
	<object>
		<name>face_M</name>
		<pose>Unspecified</pose>
		<truncated>0</truncated>
		<difficult>0</difficult>
		<bndbox>
			<xmin>104</xmin>
			<ymin>31</ymin>
			<xmax>145</xmax>
			<ymax>76</ymax>
		</bndbox>
	</object>
	<object>
		<name>C_jacket</name>
		<pose>Unspecified</pose>
		<truncated>0</truncated>
		<difficult>0</difficult>
		<bndbox>
			<xmin>33</xmin>
			<ymin>69</ymin>
			<xmax>221</xmax>
			<ymax>275</ymax>
		</bndbox>
	</object>
</annotation>