<annotation>
	<folder>glenna_tailored_skirt</folder>
	<filename>glenna_tailored_skirt41.jpg</filename>
	<path>C:\Users\陳怡靜\Desktop\glenna_tailored_skirt\glenna_tailored_skirt41.jpg</path>
	<source>
		<database>Unknown</database>
	</source>
	<size>
		<width>225</width>
		<height>225</height>
		<depth>3</depth>
	</size>
	<segmented>0</segmented>
	<object>
		<name>F_tailored skirt</name>
		<pose>Unspecified</pose>
		<truncated>0</truncated>
		<difficult>0</difficult>
		<bndbox>
			<xmin>86</xmin>
			<ymin>65</ymin>
			<xmax>146</xmax>
			<ymax>141</ymax>
		</bndbox>
	</object>
	<object>
		<name>F_shirt</name>
		<pose>Unspecified</pose>
		<truncated>0</truncated>
		<difficult>0</difficult>
		<bndbox>
			<xmin>80</xmin>
			<ymin>17</ymin>
			<xmax>147</xmax>
			<ymax>99</ymax>
		</bndbox>
	</object>
</annotation>
