<annotation>
	<folder>dress2</folder>
	<filename>sam_f152.jpg</filename>
	<path>/Users/mingshenglyu/Desktop/dress2/sam_f152.jpg</path>
	<source>
		<database>Unknown</database>
	</source>
	<size>
		<width>225</width>
		<height>225</height>
		<depth>3</depth>
	</size>
	<segmented>0</segmented>
	<object>
		<name>F_shirt</name>
		<pose>Unspecified</pose>
		<truncated>0</truncated>
		<difficult>0</difficult>
		<bndbox>
			<xmin>16</xmin>
			<ymin>45</ymin>
			<xmax>100</xmax>
			<ymax>111</ymax>
		</bndbox>
	</object>
	<object>
		<name>F_tailored skirt</name>
		<pose>Unspecified</pose>
		<truncated>0</truncated>
		<difficult>0</difficult>
		<bndbox>
			<xmin>29</xmin>
			<ymin>106</ymin>
			<xmax>101</xmax>
			<ymax>214</ymax>
		</bndbox>
	</object>
	<object>
		<name>F_tailored skirt</name>
		<pose>Unspecified</pose>
		<truncated>0</truncated>
		<difficult>0</difficult>
		<bndbox>
			<xmin>114</xmin>
			<ymin>107</ymin>
			<xmax>191</xmax>
			<ymax>218</ymax>
		</bndbox>
	</object>
	<object>
		<name>F_shirt</name>
		<pose>Unspecified</pose>
		<truncated>0</truncated>
		<difficult>0</difficult>
		<bndbox>
			<xmin>120</xmin>
			<ymin>45</ymin>
			<xmax>208</xmax>
			<ymax>114</ymax>
		</bndbox>
	</object>
</annotation>
