<?xml version='1.0' encoding='utf-8'?>
<annotation>
	<folder>dress2</folder>
	<filename>sam_f119.jpg</filename>
	<path>/Users/mingshenglyu/Desktop/dress2/sam_f119.jpg</path>
	<source>
		<database>Unknown</database>
	</source>
	<size>
		<width>800</width>
		<height>951</height>
		<depth>3</depth>
	</size>
	<segmented>0</segmented>
	<object>
		<name>F_W_suit jacket</name>
		<pose>Unspecified</pose>
		<truncated>0</truncated>
		<difficult>0</difficult>
		<bndbox>
			<xmin>284</xmin>
			<ymin>174</ymin>
			<xmax>680</xmax>
			<ymax>644</ymax>
		</bndbox>
	</object>
	<object>
		<name>F_tailored skirt</name>
		<pose>Unspecified</pose>
		<truncated>0</truncated>
		<difficult>0</difficult>
		<bndbox>
			<xmin>310</xmin>
			<ymin>599</ymin>
			<xmax>582</xmax>
			<ymax>878</ymax>
		</bndbox>
	</object>
</annotation>