<?xml version='1.0' encoding='utf-8'?>
<annotation>
	<folder>temp_picture</folder>
	<filename>Smart_casual_M877.jpg</filename>
	<path>/Users/NeilHuang/Desktop/工作/中國信託/輪調/視覺實驗室/風格辨識/All_xml_img_data/temp_picture/Smart_casual_M877.jpg</path>
	<source>
		<database>Unknown</database>
	</source>
	<size>
		<width>468</width>
		<height>624</height>
		<depth>3</depth>
	</size>
	<segmented>0</segmented>
	<object>
		<name>S_shirt</name>
		<pose>Unspecified</pose>
		<truncated>1</truncated>
		<difficult>0</difficult>
		<bndbox>
			<xmin>6</xmin>
			<ymin>12</ymin>
			<xmax>468</xmax>
			<ymax>623</ymax>
		</bndbox>
	</object>
</annotation>