<?xml version='1.0' encoding='utf-8'?>
<annotation>
	<folder>Smart casual_M</folder>
	<filename>Smart casual_M632.jpg</filename>
	<path>D:\動工中\Smart casual_M\Smart casual_M632.jpg</path>
	<source>
		<database>Unknown</database>
	</source>
	<size>
		<width>468</width>
		<height>702</height>
		<depth>3</depth>
	</size>
	<segmented>0</segmented>
	<object>
		<name>face_M</name>
		<pose>Unspecified</pose>
		<truncated>0</truncated>
		<difficult>0</difficult>
		<bndbox>
			<xmin>192</xmin>
			<ymin>75</ymin>
			<xmax>305</xmax>
			<ymax>166</ymax>
		</bndbox>
	</object>
	<object>
		<name>S_shirt</name>
		<pose>Unspecified</pose>
		<truncated>0</truncated>
		<difficult>0</difficult>
		<bndbox>
			<xmin>129</xmin>
			<ymin>175</ymin>
			<xmax>350</xmax>
			<ymax>545</ymax>
		</bndbox>
	</object>
</annotation>