<?xml version='1.0' encoding='utf-8'?>
<annotation>
	<folder>Smart casual_M</folder>
	<filename>Smart casual_M818.jpg</filename>
	<path>D:\動工中\Smart casual_M\Smart casual_M818.jpg</path>
	<source>
		<database>Unknown</database>
	</source>
	<size>
		<width>468</width>
		<height>702</height>
		<depth>3</depth>
	</size>
	<segmented>0</segmented>
	<object>
		<name>face_M</name>
		<pose>Unspecified</pose>
		<truncated>0</truncated>
		<difficult>0</difficult>
		<bndbox>
			<xmin>187</xmin>
			<ymin>85</ymin>
			<xmax>264</xmax>
			<ymax>216</ymax>
		</bndbox>
	</object>
	<object>
		<name>S_shirt</name>
		<pose>Unspecified</pose>
		<truncated>0</truncated>
		<difficult>0</difficult>
		<bndbox>
			<xmin>25</xmin>
			<ymin>206</ymin>
			<xmax>370</xmax>
			<ymax>551</ymax>
		</bndbox>
	</object>
	<object>
		<name>F_belt</name>
		<pose>Unspecified</pose>
		<truncated>0</truncated>
		<difficult>0</difficult>
		<bndbox>
			<xmin>145</xmin>
			<ymin>554</ymin>
			<xmax>325</xmax>
			<ymax>578</ymax>
		</bndbox>
	</object>
</annotation>