<annotation>
	<folder>女生blouse</folder>
	<filename>1078.jpg</filename>
	<path>D:\動工中\女生blouse\1078.jpg</path>
	<source>
		<database>Unknown</database>
	</source>
	<size>
		<width>389</width>
		<height>280</height>
		<depth>3</depth>
	</size>
	<segmented>0</segmented>
	<object>
		<name>C_short blouse</name>
		<pose>Unspecified</pose>
		<truncated>1</truncated>
		<difficult>0</difficult>
		<bndbox>
			<xmin>36</xmin>
			<ymin>1</ymin>
			<xmax>389</xmax>
			<ymax>260</ymax>
		</bndbox>
	</object>
</annotation>
