<annotation>
	<folder>皮帶</folder>
	<filename>F_belt266.jpg</filename>
	<path>C:\Users\Dale\Desktop\皮帶\F_belt266.jpg</path>
	<source>
		<database>Unknown</database>
	</source>
	<size>
		<width>473</width>
		<height>593</height>
		<depth>3</depth>
	</size>
	<segmented>0</segmented>
	<object>
		<name>F_belt</name>
		<pose>Unspecified</pose>
		<truncated>0</truncated>
		<difficult>0</difficult>
		<bndbox>
			<xmin>2</xmin>
			<ymin>263</ymin>
			<xmax>247</xmax>
			<ymax>316</ymax>
		</bndbox>
	</object>
</annotation>
