<?xml version='1.0' encoding='utf-8'?>
<annotation>
	<folder>Formal4</folder>
	<filename>Formal_M191.jpg</filename>
	<path>C:\Users\Dale\Desktop\工作穿著準則-20190708T072430Z-001\Formal4\Formal_M191.jpg</path>
	<source>
		<database>Unknown</database>
	</source>
	<size>
		<width>300</width>
		<height>300</height>
		<depth>3</depth>
	</size>
	<segmented>0</segmented>
	<object>
		<name>face_M</name>
		<pose>Unspecified</pose>
		<truncated>0</truncated>
		<difficult>0</difficult>
		<bndbox>
			<xmin>138</xmin>
			<ymin>23</ymin>
			<xmax>167</xmax>
			<ymax>53</ymax>
		</bndbox>
	</object>
	<object>
		<name>C_jacket</name>
		<pose>Unspecified</pose>
		<truncated>0</truncated>
		<difficult>0</difficult>
		<bndbox>
			<xmin>101</xmin>
			<ymin>44</ymin>
			<xmax>189</xmax>
			<ymax>154</ymax>
		</bndbox>
	</object>
	<object>
		<name>C_M_pants</name>
		<pose>Unspecified</pose>
		<truncated>0</truncated>
		<difficult>0</difficult>
		<bndbox>
			<xmin>121</xmin>
			<ymin>143</ymin>
			<xmax>184</xmax>
			<ymax>237</ymax>
		</bndbox>
	</object>
	<object>
		<name>C_sneakers</name>
		<pose>Unspecified</pose>
		<truncated>0</truncated>
		<difficult>0</difficult>
		<bndbox>
			<xmin>119</xmin>
			<ymin>243</ymin>
			<xmax>147</xmax>
			<ymax>282</ymax>
		</bndbox>
	</object>
	<object>
		<name>C_sneakers</name>
		<pose>Unspecified</pose>
		<truncated>0</truncated>
		<difficult>0</difficult>
		<bndbox>
			<xmin>154</xmin>
			<ymin>237</ymin>
			<xmax>191</xmax>
			<ymax>267</ymax>
		</bndbox>
	</object>
</annotation>