<annotation>
	<folder>glenna_tailored_skirt</folder>
	<filename>glenna_tailored_skirt282.jpg</filename>
	<path>C:\Users\陳怡靜\Desktop\glenna_tailored_skirt\glenna_tailored_skirt282.jpg</path>
	<source>
		<database>Unknown</database>
	</source>
	<size>
		<width>195</width>
		<height>259</height>
		<depth>3</depth>
	</size>
	<segmented>0</segmented>
	<object>
		<name>F_tailored skirt</name>
		<pose>Unspecified</pose>
		<truncated>1</truncated>
		<difficult>0</difficult>
		<bndbox>
			<xmin>63</xmin>
			<ymin>156</ymin>
			<xmax>157</xmax>
			<ymax>259</ymax>
		</bndbox>
	</object>
</annotation>
