<annotation>
	<folder>連身裙___Google_搜尋</folder>
	<filename>S_suit386.jpg</filename>
	<path>C:\Users\Dale\Desktop\連身裙___Google_搜尋\S_suit386.jpg</path>
	<source>
		<database>Unknown</database>
	</source>
	<size>
		<width>168</width>
		<height>168</height>
		<depth>3</depth>
	</size>
	<segmented>0</segmented>
	<object>
		<name>C_dress</name>
		<pose>Unspecified</pose>
		<truncated>0</truncated>
		<difficult>0</difficult>
		<bndbox>
			<xmin>14</xmin>
			<ymin>37</ymin>
			<xmax>93</xmax>
			<ymax>161</ymax>
		</bndbox>
	</object>
	<object>
		<name>C_dress</name>
		<pose>Unspecified</pose>
		<truncated>0</truncated>
		<difficult>0</difficult>
		<bndbox>
			<xmin>99</xmin>
			<ymin>27</ymin>
			<xmax>146</xmax>
			<ymax>129</ymax>
		</bndbox>
	</object>
</annotation>
